{
    "background-color": "#0a0a07",
    "badge-color": "#c1c1c1",
    "bold-color": "#c1c1c1",
    "comment": "",
    "cursor-background-color": "#0a0a07",
    "cursor-foreground-color": "#c1c1c1",
    "foreground-color": "#c1c1c1",
    "highlight-background-color": "#0a0a07",
    "highlight-foreground-color": "#c1c1c1",
    "name": "wal export",
    "palette": [
        "#0a0a07",
        "#2d7b87",
        "#388bab",
        "#935f31",
        "#c4974f",
        "#c99a5d",
        "#d1ac74",
        "#c1c1c1",
        "#676754",
        "#2d7b87",
        "#388bab",
        "#935f31",
        "#c4974f",
        "#c99a5d",
        "#d1ac74",
        "#c1c1c1"
    ],
    "use-badge-color": false,
    "use-bold-color": false,
    "use-cursor-color": false,
    "use-highlight-color": false,
    "use-theme-colors": false
}
